pelican/plugins/feed_filter/__init__.py
pelican/plugins/feed_filter/feed_filter.py
pelican/plugins/feed_filter/test_feed_filter.py
pelican_feed_filter-1.1.0.dist-info/METADATA
pelican_feed_filter-1.1.0.dist-info/WHEEL
pelican_feed_filter-1.1.0.dist-info/LICENSE
pelican_feed_filter-1.1.0.dist-info/RECORD
